stored_agent.py
stored_agent-0.1.3.dist-info/METADATA
stored_agent-0.1.3.dist-info/WHEEL
stored_agent-0.1.3.dist-info/RECORD
