Metadata-Version: 2.1
Name: stored-agent
Version: 0.1.3
Summary: A framework for building agents that persist state between interactions.
Author: Vijay Balasubramaniam
Author-email: vbalasu@gmail.com
Requires-Python: >=3.9,<4.0
Classifier: Programming Language :: Python :: 3
Classifier: Programming Language :: Python :: 3.9
Classifier: Programming Language :: Python :: 3.10
Classifier: Programming Language :: Python :: 3.11
Classifier: Programming Language :: Python :: 3.12
Classifier: Programming Language :: Python :: 3.13
Requires-Dist: boto3 (>=1.35.60,<2.0.0)
Requires-Dist: fs (>=2.4.16,<3.0.0)
Requires-Dist: fs-s3fs (>=1.1.1,<2.0.0)
